ceos_alos2/__init__.py
ceos_alos2/array.py
ceos_alos2/common.py
ceos_alos2/datatypes.py
ceos_alos2/decoders.py
ceos_alos2/dicttoolz.py
ceos_alos2/hierarchy.py
ceos_alos2/io.py
ceos_alos2/summary.py
ceos_alos2/testing.py
ceos_alos2/transformers.py
ceos_alos2/utils.py
ceos_alos2/xarray.py
ceos_alos2/sar_image/__init__.py
ceos_alos2/sar_image/__main__.py
ceos_alos2/sar_image/cli.py
ceos_alos2/sar_image/enums.py
ceos_alos2/sar_image/file_descriptor.py
ceos_alos2/sar_image/io.py
ceos_alos2/sar_image/metadata.py
ceos_alos2/sar_image/processed_data.py
ceos_alos2/sar_image/signal_data.py
ceos_alos2/sar_image/caching/__init__.py
ceos_alos2/sar_image/caching/decoders.py
ceos_alos2/sar_image/caching/encoders.py
ceos_alos2/sar_image/caching/path.py
ceos_alos2/sar_leader/__init__.py
ceos_alos2/sar_leader/attitude.py
ceos_alos2/sar_leader/data_quality_summary.py
ceos_alos2/sar_leader/dataset_summary.py
ceos_alos2/sar_leader/facility_related_data.py
ceos_alos2/sar_leader/file_descriptor.py
ceos_alos2/sar_leader/io.py
ceos_alos2/sar_leader/map_projection.py
ceos_alos2/sar_leader/metadata.py
ceos_alos2/sar_leader/platform_position.py
ceos_alos2/sar_leader/radiometric_data.py
ceos_alos2/sar_leader/structure.py
ceos_alos2/sar_trailer/__init__.py
ceos_alos2/sar_trailer/file_descriptor.py
ceos_alos2/sar_trailer/image_data.py
ceos_alos2/tests/__init__.py
ceos_alos2/tests/test_array.py
ceos_alos2/tests/test_caching.py
ceos_alos2/tests/test_datatypes.py
ceos_alos2/tests/test_decoders.py
ceos_alos2/tests/test_dicttoolz.py
ceos_alos2/tests/test_hierarchy.py
ceos_alos2/tests/test_sar_image.py
ceos_alos2/tests/test_sar_leader.py
ceos_alos2/tests/test_summary.py
ceos_alos2/tests/test_testing.py
ceos_alos2/tests/test_transformers.py
ceos_alos2/tests/test_utils.py
ceos_alos2/tests/test_volume_directory.py
ceos_alos2/tests/test_xarray.py
ceos_alos2/tests/utils.py
ceos_alos2/volume_directory/__init__.py
ceos_alos2/volume_directory/io.py
ceos_alos2/volume_directory/metadata.py
xarray_ceos_alos2-2025.5.0.dist-info/licenses/LICENSE
xarray_ceos_alos2-2025.5.0.dist-info/METADATA
xarray_ceos_alos2-2025.5.0.dist-info/WHEEL
xarray_ceos_alos2-2025.5.0.dist-info/entry_points.txt
xarray_ceos_alos2-2025.5.0.dist-info/top_level.txt
xarray_ceos_alos2-2025.5.0.dist-info/RECORD
